raid/__init__.py
raid/data/__init__.py
raid/data/concrete/__init__.py
raid/data/concrete/image_single_clf_dataset.py
raid/data/concrete/image_single_clf_sample.py
raid/data/functional/__init__.py
raid/data/functional/resampler.py
raid/data/functional/sample_distribution.py
raid/data/functional/score_counter.py
raid/data/functional/stratifier.py
raid/data/interface/__init__.py
raid/data/interface/i_dataset.py
raid/data/interface/i_image_sample.py
raid/data/interface/i_sample.py
raid/data/interface/i_single_clf_sample.py
raid/logic/__init__.py
raid/logic/checkpoint.py
raid/logic/config.py
raid/logic/engine.py
raid/logic/grid_search.py
raid/logic/limit_type.py
raid/logic/metric.py
raid/logic/trainer.py
raid/visual/__init__.py
raid/visual/data_renderer.py
raid/visual/plotter.py
raid-0.3.64.data/scripts/raid
raid-0.3.64.dist-info/DESCRIPTION.rst
raid-0.3.64.dist-info/METADATA
raid-0.3.64.dist-info/RECORD
raid-0.3.64.dist-info/WHEEL
raid-0.3.64.dist-info/metadata.json
raid-0.3.64.dist-info/top_level.txt
