Metadata-Version: 2.0
Name: raid
Version: 0.3.64
Summary: A utility package to help with Pytorch training.
Home-page: https://github.com/krinj/torch-raptor
Author: Jakrin Juangbhanich
Author-email: juangbhanich.k@gmail.com
License: UNKNOWN
Platform: UNKNOWN
Classifier: Programming Language :: Python :: 3.6
